tools/__init__.py
tools/dna.py
tools/rna.py
toolsForDna-0.0.4.dist-info/LICENSE
toolsForDna-0.0.4.dist-info/METADATA
toolsForDna-0.0.4.dist-info/WHEEL
toolsForDna-0.0.4.dist-info/top_level.txt
toolsForDna-0.0.4.dist-info/RECORD
