Metadata-Version: 2.1
Name: toolsForDna
Version: 0.0.4
Summary: Tools for DNA
Home-page: UNKNOWN
Author: TheOnlyWalrus
Author-email: UNKNOWN
License: UNKNOWN
Platform: UNKNOWN
